{"shortname": "73717", "longname": "73717, USA", "source": "Census", "article_type": "ZIP", "rows": [{"statname": "Population", "statval": 6943.0, "ordinal": 11624, "overall_ordinal": 54141, "percentile_by_population": 0.11129176765305104}, {"statname": "PW Density (r=1km)", "statval": 444.8559688671758, "ordinal": 10063, "overall_ordinal": 60423, "percentile_by_population": 0.21843148471236584}, {"statname": "AW Density", "statval": 4.072076435232986, "ordinal": 27803, "overall_ordinal": 134500, "percentile_by_population": 0.012066755382649563}, {"statname": "White %", "statval": 0.8026789572231025, "ordinal": 18463, "overall_ordinal": 80183, "percentile_by_population": 0.7527069048343709}, {"statname": "Hispanic %", "statval": 0.07475154832205098, "ordinal": 10959, "overall_ordinal": 54135, "percentile_by_population": 0.3857518287511882}, {"statname": "Black %", "statval": 0.03226271064381391, "ordinal": 11036, "overall_ordinal": 56329, "percentile_by_population": 0.39302063124701603}, {"statname": "Asian %", "statval": 0.01022612703442316, "ordinal": 11209, "overall_ordinal": 60157, "percentile_by_population": 0.2853544558745079}, {"statname": "Native %", "statval": 0.029814201353881607, "ordinal": 1907, "overall_ordinal": 9737, "percentile_by_population": 0.9719548714569664}, {"statname": "Hawaiian / PI %", "statval": 0.00014402995823131211, "ordinal": 14438, "overall_ordinal": 69418, "percentile_by_population": 0.22113353086934684}, {"statname": "Other / Mixed %", "statval": 0.05012242546449662, "ordinal": 9171, "overall_ordinal": 43604, "percentile_by_population": 0.6745380706597274}, {"statname": "High School %", "statval": 0.9242724850493824, "ordinal": 13990, "overall_ordinal": 65401, "percentile_by_population": 0.5786525295529501}, {"statname": "Undergrad %", "statval": 0.3221775527074402, "ordinal": 8054, "overall_ordinal": 40183, "percentile_by_population": 0.5790896850171441}, {"statname": "Grad %", "statval": 0.10305579913404067, "ordinal": 9921, "overall_ordinal": 49337, "percentile_by_population": 0.5200215278253884}, {"statname": "Undergrad STEM %", "statval": 0.4188940499199677, "ordinal": 17175, "overall_ordinal": 79602, "percentile_by_population": 0.4118203869720799}, {"statname": "Undergrad Humanities %", "statval": 0.3879800740248806, "ordinal": 16052, "overall_ordinal": 73619, "percentile_by_population": 0.6737931302341641}, {"statname": "Undergrad Business %", "statval": 0.19312587605515175, "ordinal": 14031, "overall_ordinal": 66092, "percentile_by_population": 0.41740761795673453}, {"statname": "Silent %", "statval": 0.07522076083363809, "ordinal": 14706, "overall_ordinal": 65676, "percentile_by_population": 0.7109817278589892}, {"statname": "Boomer %", "statval": 0.19945669257578386, "ordinal": 27665, "overall_ordinal": 125344, "percentile_by_population": 0.3106572046643685}, {"statname": "Gen X %", "statval": 0.11982570464864767, "ordinal": 30967, "overall_ordinal": 143483, "percentile_by_population": 0.0212538121194753}, {"statname": "Millennial %", "statval": 0.2143449985297926, "ordinal": 6153, "overall_ordinal": 31665, "percentile_by_population": 0.6489165764972639}, {"statname": "Gen Z %", "statval": 0.27951032054573255, "ordinal": 1374, "overall_ordinal": 6883, "percentile_by_population": 0.9590696201735823}, {"statname": "Gen Alpha %", "statval": 0.11164152286640533, "ordinal": 16821, "overall_ordinal": 82059, "percentile_by_population": 0.3742604172672781}, {"statname": "Household Income < $50k %", "statval": 0.47880419374133804, "ordinal": 9645, "overall_ordinal": 43432, "percentile_by_population": 0.7677509806281126}, {"statname": "Household Income $50k - $100k %", "statval": 0.25960706494435004, "ordinal": 26110, "overall_ordinal": 121364, "percentile_by_population": 0.24355437578342443}, {"statname": "Household Income > $100k %", "statval": 0.26158874131431187, "ordinal": 15832, "overall_ordinal": 75143, "percentile_by_population": 0.38734270495108425}, {"statname": "Individual Income < $50k %", "statval": 0.7507188642584521, "ordinal": 10325, "overall_ordinal": 45025, "percentile_by_population": 0.7604225472798913}, {"statname": "Individual Income $50k - $100k %", "statval": 0.1709249955608611, "ordinal": 26208, "overall_ordinal": 123524, "percentile_by_population": 0.15643871150792021}, {"statname": "Individual Income > $100k %", "statval": 0.07835614018068687, "ordinal": 13527, "overall_ordinal": 64761, "percentile_by_population": 0.44209483566937113}, {"statname": "Housing Units per Adult", "statval": 0.5695364238410596, "ordinal": 17479, "overall_ordinal": 77967, "percentile_by_population": 0.6932770899293017}, {"statname": "Vacancy %", "statval": 0.20678818353236958, "ordinal": 6772, "overall_ordinal": 25378, "percentile_by_population": 0.9544947779915516}, {"statname": "1BR Rent < $750 %", "statval": 0.5670275870375491, "ordinal": 15786, "overall_ordinal": 71124, "percentile_by_population": 0.7066734137141446}, {"statname": "1BR Rent $750 - $1500 %", "statval": 0.432972412962451, "ordinal": 9687, "overall_ordinal": 45482, "percentile_by_population": 0.47284320860409257}, {"statname": "1BR Rent > $1500 %", "statval": 0.0, "ordinal": 24400, "overall_ordinal": 64621, "percentile_by_population": 0.08741642118692194}, {"statname": "2BR Rent < $750 %", "statval": 0.56008388531568, "ordinal": 10988, "overall_ordinal": 46788, "percentile_by_population": 0.8913279499187854}, {"statname": "2BR Rent $750 - $1500 %", "statval": 0.4083083798209628, "ordinal": 17468, "overall_ordinal": 84194, "percentile_by_population": 0.3371359326695603}, {"statname": "2BR Rent > $1500 %", "statval": 0.031607734863357266, "ordinal": 11043, "overall_ordinal": 54303, "percentile_by_population": 0.3236081437122428}, {"statname": "Commute Car %", "statval": 0.9055408087290957, "ordinal": 12114, "overall_ordinal": 53168, "percentile_by_population": 0.7548101623307424}, {"statname": "Commute Bike %", "statval": 6.47565174985926e-05, "ordinal": 15689, "overall_ordinal": 74574, "percentile_by_population": 0.19877329392175036}, {"statname": "Commute Walk %", "statval": 0.05802341907994659, "ordinal": 3904, "overall_ordinal": 18312, "percentile_by_population": 0.9180131926298609}, {"statname": "Commute Transit %", "statval": 0.0, "ordinal": 29826, "overall_ordinal": 98586, "percentile_by_population": 0.024314835649290933}, {"statname": "Commute Work From Home %", "statval": 0.0281032851201456, "ordinal": 28154, "overall_ordinal": 130951, "percentile_by_population": 0.057560243057697025}, {"statname": "Commute Time < 15 min %", "statval": 0.7490653287000781, "ordinal": 455, "overall_ordinal": 1880, "percentile_by_population": 0.9972280259412495}, {"statname": "Commute Time 15 - 29 min %", "statval": 0.11509850352143101, "ordinal": 31846, "overall_ordinal": 148290, "percentile_by_population": 0.005752285574435079}, {"statname": "Commute Time 30 - 59 min %", "statval": 0.10200637256214358, "ordinal": 30663, "overall_ordinal": 141288, "percentile_by_population": 0.04550310941009994}, {"statname": "Commute Time > 60 min %", "statval": 0.03382979521634716, "ordinal": 27075, "overall_ordinal": 122565, "percentile_by_population": 0.1494047660027502}, {"statname": "2020 Presidential Election", "statval": -0.6260744922880727, "ordinal": 27592, "overall_ordinal": 131131, "percentile_by_population": 0.04378773034911809}, {"statname": "2016 Presidential Election", "statval": -0.6320217126642288, "ordinal": 28467, "overall_ordinal": 134705, "percentile_by_population": 0.03968894890779806}, {"statname": "PW Density (r=250m)", "statval": 844.8112176261983, "ordinal": 13010, "overall_ordinal": 73981, "percentile_by_population": 0.13187225553454152}, {"statname": "PW Density (r=500m)", "statval": 609.4988348030664, "ordinal": 10639, "overall_ordinal": 62872, "percentile_by_population": 0.20092453459249215}, {"statname": "PW Density (r=2km)", "statval": 262.4751091621331, "ordinal": 10635, "overall_ordinal": 63830, "percentile_by_population": 0.18826961629142136}, {"statname": "PW Density (r=4km)", "statval": 96.20000532866831, "ordinal": 12902, "overall_ordinal": 74842, "percentile_by_population": 0.1286356443043679}], "related": {"same_geography": [], "contained_by": [{"longname": "Oklahoma, USA", "shortname": "Oklahoma", "row_type": "State"}, {"longname": "Historical Congressional District OK-3, 113th-117th Congress, USA", "shortname": "OK-03 [113th-117th Congress]", "row_type": "Historical Congressional District"}, {"longname": "Historical Congressional District OK-3, 108th-112th Congress, USA", "shortname": "OK-03 [108th-112th Congress]", "row_type": "Historical Congressional District"}, {"longname": "Historical Congressional District OK-6, 103rd-107th Congress, USA", "shortname": "OK-06 [103rd-107th Congress]", "row_type": "Historical Congressional District"}, {"longname": "Historical Congressional District OK-6, 98th-102nd Congress, USA", "shortname": "OK-06 [98th-102nd Congress]", "row_type": "Historical Congressional District"}, {"longname": "Historical Congressional District OK-6, 93rd-97th Congress, USA", "shortname": "OK-06 [93rd-97th Congress]", "row_type": "Historical Congressional District"}, {"longname": "Historical Congressional District OK-6, 91st-92nd Congress, USA", "shortname": "OK-06 [91st-92nd Congress]", "row_type": "Historical Congressional District"}, {"longname": "Historical Congressional District OK-1, 83rd-90th Congress, USA", "shortname": "OK-01 [83rd-90th Congress]", "row_type": "Historical Congressional District"}, {"longname": "Historical Congressional District OK-8, 78th-82nd Congress, USA", "shortname": "OK-08 [78th-82nd Congress]", "row_type": "Historical Congressional District"}, {"longname": "Historical Congressional District OK-8, 73rd-77th Congress, USA", "shortname": "OK-08 [73rd-77th Congress]", "row_type": "Historical Congressional District"}, {"longname": "Historical Congressional District OK-8, 64th-72nd Congress, USA", "shortname": "OK-08 [64th-72nd Congress]", "row_type": "Historical Congressional District"}, {"longname": "Historical Congressional District OK-2, 63rd Congress, USA", "shortname": "OK-02 [63rd Congress]", "row_type": "Historical Congressional District"}, {"longname": "Historical Congressional District OK-2, 60th-62nd Congress, USA", "shortname": "OK-02 [60th-62nd Congress]", "row_type": "Historical Congressional District"}, {"longname": "OK-HD058, USA", "shortname": "OK-HD058", "row_type": "State House District"}, {"longname": "OK-03, USA", "shortname": "OK-03", "row_type": "Congressional District"}], "contains": [{"longname": "Alva CCD [CCD], Woods County, Oklahoma, USA", "shortname": "Alva CCD", "row_type": "CCD"}, {"longname": "Alva city, Oklahoma, USA", "shortname": "Alva city", "row_type": "City"}, {"longname": "Avard CDP, Oklahoma, USA", "shortname": "Avard CDP", "row_type": "City"}, {"longname": "Capron town, Oklahoma, USA", "shortname": "Capron town", "row_type": "City"}], "borders": [{"longname": "67029, USA", "shortname": "67029", "row_type": "ZIP"}, {"longname": "67057, USA", "shortname": "67057", "row_type": "ZIP"}, {"longname": "67070, USA", "shortname": "67070", "row_type": "ZIP"}, {"longname": "67071, USA", "shortname": "67071", "row_type": "ZIP"}, {"longname": "73716, USA", "shortname": "73716", "row_type": "ZIP"}, {"longname": "73722, USA", "shortname": "73722", "row_type": "ZIP"}, {"longname": "73726, USA", "shortname": "73726", "row_type": "ZIP"}, {"longname": "73728, USA", "shortname": "73728", "row_type": "ZIP"}, {"longname": "73731, USA", "shortname": "73731", "row_type": "ZIP"}, {"longname": "73746, USA", "shortname": "73746", "row_type": "ZIP"}, {"longname": "73842, USA", "shortname": "73842", "row_type": "ZIP"}, {"longname": "73860, USA", "shortname": "73860", "row_type": "ZIP"}], "intersects": [{"longname": "Alfalfa County, Oklahoma, USA", "shortname": "Alfalfa County", "row_type": "County"}, {"longname": "Woods County, Oklahoma, USA", "shortname": "Woods County", "row_type": "County"}, {"longname": "OK-SD019, USA", "shortname": "OK-SD019", "row_type": "State Senate District"}, {"longname": "OK-SD027, USA", "shortname": "OK-SD027", "row_type": "State Senate District"}, {"longname": "Cherokee CCD [CCD], Alfalfa County, Oklahoma, USA", "shortname": "Cherokee CCD", "row_type": "CCD"}, {"longname": "North Alfalfa CCD [CCD], Alfalfa County, Oklahoma, USA", "shortname": "North Alfalfa CCD", "row_type": "CCD"}, {"longname": "South Woods CCD [CCD], Woods County, Oklahoma, USA", "shortname": "South Woods CCD", "row_type": "CCD"}, {"longname": "West Woods CCD [CCD], Woods County, Oklahoma, USA", "shortname": "West Woods CCD", "row_type": "CCD"}, {"longname": "Hopeton CDP, Oklahoma, USA", "shortname": "Hopeton CDP", "row_type": "City"}, {"longname": "Alva Public Schools, Oklahoma, USA", "shortname": "Alva Public Schools", "row_type": "School District"}, {"longname": "Cherokee Public Schools, Oklahoma, USA", "shortname": "Cherokee Public Schools", "row_type": "School District"}, {"longname": "Freedom Public Schools, Oklahoma, USA", "shortname": "Freedom Public Schools", "row_type": "School District"}, {"longname": "Waynoka Public Schools, Oklahoma, USA", "shortname": "Waynoka Public Schools", "row_type": "School District"}]}}