{"shortname": "92273", "longname": "92273, USA", "source": "Census", "article_type": "ZIP", "rows": [{"statname": "Population", "statval": 1728.0, "ordinal": 19476, "overall_ordinal": 89142, "percentile_by_population": 0.025902666958498077}, {"statname": "PW Density (r=1km)", "statval": 455.51397321248857, "ordinal": 9948, "overall_ordinal": 59684, "percentile_by_population": 0.22260545612856952}, {"statname": "AW Density", "statval": 95.61160568100745, "ordinal": 11552, "overall_ordinal": 74349, "percentile_by_population": 0.23692869663235927}, {"statname": "White %", "statval": 0.07465277777777778, "ordinal": 32056, "overall_ordinal": 147010, "percentile_by_population": 0.058973780520980235}, {"statname": "Hispanic %", "statval": 0.8819444444444444, "ordinal": 312, "overall_ordinal": 2362, "percentile_by_population": 0.9779702517227568}, {"statname": "Black %", "statval": 0.017939814814814815, "ordinal": 13635, "overall_ordinal": 69176, "percentile_by_population": 0.2710653306965237}, {"statname": "Asian %", "statval": 0.00636574074074074, "ordinal": 14699, "overall_ordinal": 76740, "percentile_by_population": 0.1884444748913593}, {"statname": "Native %", "statval": 0.003472222222222222, "ordinal": 11686, "overall_ordinal": 53188, "percentile_by_population": 0.7233178798706419}, {"statname": "Hawaiian / PI %", "statval": 0.0, "ordinal": 32257, "overall_ordinal": 92282, "percentile_by_population": 0.0016630900107696966}, {"statname": "Other / Mixed %", "statval": 0.015625, "ordinal": 30644, "overall_ordinal": 140274, "percentile_by_population": 0.04279800939808054}, {"statname": "High School %", "statval": 0.7475484738383018, "ordinal": 31440, "overall_ordinal": 145943, "percentile_by_population": 0.06426371483309623}, {"statname": "Undergrad %", "statval": 0.0926101152861828, "ordinal": 30425, "overall_ordinal": 142417, "percentile_by_population": 0.02970272639572047}, {"statname": "Grad %", "statval": 0.005618617065957279, "ordinal": 32446, "overall_ordinal": 150437, "percentile_by_population": 0.0010835657370803498}, {"statname": "Undergrad STEM %", "statval": 0.3730875929142811, "ordinal": 23246, "overall_ordinal": 109239, "percentile_by_population": 0.16809082688402177}, {"statname": "Undergrad Humanities %", "statval": 0.3704702220403215, "ordinal": 18481, "overall_ordinal": 85730, "percentile_by_population": 0.5780157828487469}, {"statname": "Undergrad Business %", "statval": 0.2564421850453974, "ordinal": 5251, "overall_ordinal": 24080, "percentile_by_population": 0.8369700563477491}, {"statname": "Silent %", "statval": 0.021908530233315612, "ordinal": 31840, "overall_ordinal": 147103, "percentile_by_population": 0.024423698708741615}, {"statname": "Boomer %", "statval": 0.2106900975636517, "ordinal": 26056, "overall_ordinal": 117305, "percentile_by_population": 0.39519718724054187}, {"statname": "Gen X %", "statval": 0.1151784350814454, "ordinal": 31249, "overall_ordinal": 145019, "percentile_by_population": 0.018135028298180145}, {"statname": "Millennial %", "statval": 0.2866036414919896, "ordinal": 1168, "overall_ordinal": 6654, "percentile_by_population": 0.9440670791988559}, {"statname": "Gen Z %", "statval": 0.1809091122016165, "ordinal": 15951, "overall_ordinal": 79367, "percentile_by_population": 0.38558080390468896}, {"statname": "Gen Alpha %", "statval": 0.18471018342798126, "ordinal": 1337, "overall_ordinal": 7408, "percentile_by_population": 0.9806521968202042}, {"statname": "Household Income < $50k %", "statval": 0.5282258064516129, "ordinal": 6077, "overall_ordinal": 27454, "percentile_by_population": 0.8569621422615002}, {"statname": "Household Income $50k - $100k %", "statval": 0.3064516129032258, "ordinal": 18031, "overall_ordinal": 83048, "percentile_by_population": 0.538942176766835}, {"statname": "Household Income > $100k %", "statval": 0.1653225806451613, "ordinal": 26856, "overall_ordinal": 125329, "percentile_by_population": 0.132863482496283}, {"statname": "Individual Income < $50k %", "statval": 0.8781725888324873, "ordinal": 879, "overall_ordinal": 4627, "percentile_by_population": 0.9807636804578043}, {"statname": "Individual Income $50k - $100k %", "statval": 0.08049311094996375, "ordinal": 32448, "overall_ordinal": 149902, "percentile_by_population": 0.011807171728153487}, {"statname": "Individual Income > $100k %", "statval": 0.041334300217548955, "ordinal": 25693, "overall_ordinal": 120326, "percentile_by_population": 0.15690185760922182}, {"statname": "Housing Units per Adult", "statval": 0.43187250996015936, "ordinal": 31378, "overall_ordinal": 145675, "percentile_by_population": 0.07946345954276746}, {"statname": "Vacancy %", "statval": 0.04981549815498155, "ordinal": 27600, "overall_ordinal": 125253, "percentile_by_population": 0.31893971969841917}, {"statname": "1BR Rent < $750 %", "statval": 0.001019367991845056, "ordinal": 24971, "overall_ordinal": 114219, "percentile_by_population": 0.09058954390633167}, {"statname": "1BR Rent $750 - $1500 %", "statval": 0.9989806320081549, "ordinal": 1775, "overall_ordinal": 8460, "percentile_by_population": 0.9797862436535992}, {"statname": "1BR Rent > $1500 %", "statval": 0.0, "ordinal": 26861, "overall_ordinal": 67083, "percentile_by_population": 0.03262958349576739}, {"statname": "2BR Rent < $750 %", "statval": 0.2048885287709382, "ordinal": 19399, "overall_ordinal": 87366, "percentile_by_population": 0.6559446623060246}, {"statname": "2BR Rent $750 - $1500 %", "statval": 0.7951114712290618, "ordinal": 5301, "overall_ordinal": 23939, "percentile_by_population": 0.839355741649075}, {"statname": "2BR Rent > $1500 %", "statval": 0.0, "ordinal": 30919, "overall_ordinal": 85778, "percentile_by_population": 0.006214084035206069}, {"statname": "Commute Car %", "statval": 0.8073344326054144, "ordinal": 25923, "overall_ordinal": 118922, "percentile_by_population": 0.26700275925065875}, {"statname": "Commute Bike %", "statval": 0.0, "ordinal": 31962, "overall_ordinal": 91654, "percentile_by_population": 0.007382500327736574}, {"statname": "Commute Walk %", "statval": 0.050707368221345174, "ordinal": 4686, "overall_ordinal": 22253, "percentile_by_population": 0.8999116162956287}, {"statname": "Commute Transit %", "statval": 0.0, "ordinal": 32049, "overall_ordinal": 100809, "percentile_by_population": 0.005293472242023478}, {"statname": "Commute Work From Home %", "statval": 0.08630901116761168, "ordinal": 12855, "overall_ordinal": 60540, "percentile_by_population": 0.5383123624928561}, {"statname": "Commute Time < 15 min %", "statval": 0.2581635755841985, "ordinal": 16122, "overall_ordinal": 82249, "percentile_by_population": 0.599931140051059}, {"statname": "Commute Time 15 - 29 min %", "statval": 0.6840861753077689, "ordinal": 113, "overall_ordinal": 787, "percentile_by_population": 0.9995099967078128}, {"statname": "Commute Time 30 - 59 min %", "statval": 0.05756819131496898, "ordinal": 32139, "overall_ordinal": 148735, "percentile_by_population": 0.007832639158018573}, {"statname": "Commute Time > 60 min %", "statval": 0.00018205779306354665, "ordinal": 32302, "overall_ordinal": 148616, "percentile_by_population": 0.001374240743508448}, {"statname": "2020 Presidential Election", "statval": 0.2752654463570674, "ordinal": 4929, "overall_ordinal": 26695, "percentile_by_population": 0.692739109438977}, {"statname": "2016 Presidential Election", "statval": 0.4690361778163396, "ordinal": 2684, "overall_ordinal": 15160, "percentile_by_population": 0.8174894044975504}, {"statname": "PW Density (r=250m)", "statval": 2028.1055451925004, "ordinal": 6305, "overall_ordinal": 33412, "percentile_by_population": 0.43923806484126693}, {"statname": "PW Density (r=500m)", "statval": 1021.3385322133458, "ordinal": 7518, "overall_ordinal": 43423, "percentile_by_population": 0.3549990154753835}, {"statname": "PW Density (r=2km)", "statval": 142.2107441765754, "ordinal": 13254, "overall_ordinal": 77720, "percentile_by_population": 0.12001571713408932}, {"statname": "PW Density (r=4km)", "statval": 46.37629287821996, "ordinal": 16393, "overall_ordinal": 90560, "percentile_by_population": 0.07248650937125922}], "related": {"same_geography": [], "contained_by": [{"longname": "California, USA", "shortname": "California", "row_type": "State"}, {"longname": "El Centro MSA, CA, USA", "shortname": "El Centro MSA", "row_type": "MSA"}, {"longname": "Imperial County, California, USA", "shortname": "Imperial County", "row_type": "County"}, {"longname": "Historical Congressional District CA-51, 113th-117th Congress, USA", "shortname": "CA-51 [113th-117th Congress]", "row_type": "Historical Congressional District"}, {"longname": "Historical Congressional District CA-51, 108th-112th Congress, USA", "shortname": "CA-51 [108th-112th Congress]", "row_type": "Historical Congressional District"}, {"longname": "Historical Congressional District CA-52, 103rd-107th Congress, USA", "shortname": "CA-52 [103rd-107th Congress]", "row_type": "Historical Congressional District"}, {"longname": "Historical Congressional District CA-45, 99th-102nd Congress, USA", "shortname": "CA-45 [99th-102nd Congress]", "row_type": "Historical Congressional District"}, {"longname": "Historical Congressional District CA-45, 98th Congress, USA", "shortname": "CA-45 [98th Congress]", "row_type": "Historical Congressional District"}, {"longname": "Historical Congressional District CA-43, 94th-97th Congress, USA", "shortname": "CA-43 [94th-97th Congress]", "row_type": "Historical Congressional District"}, {"longname": "Historical Congressional District CA-43, 93rd Congress, USA", "shortname": "CA-43 [93rd Congress]", "row_type": "Historical Congressional District"}, {"longname": "Historical Congressional District CA-38, 91st-92nd Congress, USA", "shortname": "CA-38 [91st-92nd Congress]", "row_type": "Historical Congressional District"}, {"longname": "Historical Congressional District CA-38, 88th-90th Congress, USA", "shortname": "CA-38 [88th-90th Congress]", "row_type": "Historical Congressional District"}, {"longname": "Historical Congressional District CA-29, 83rd-87th Congress, USA", "shortname": "CA-29 [83rd-87th Congress]", "row_type": "Historical Congressional District"}, {"longname": "Historical Congressional District CA-22, 78th-82nd Congress, USA", "shortname": "CA-22 [78th-82nd Congress]", "row_type": "Historical Congressional District"}, {"longname": "Historical Congressional District CA-20, 73rd-77th Congress, USA", "shortname": "CA-20 [73rd-77th Congress]", "row_type": "Historical Congressional District"}, {"longname": "Historical Congressional District CA-11, 63rd-72nd Congress, USA", "shortname": "CA-11 [63rd-72nd Congress]", "row_type": "Historical Congressional District"}, {"longname": "Historical Congressional District CA-8, 58th-62nd Congress, USA", "shortname": "CA-08 [58th-62nd Congress]", "row_type": "Historical Congressional District"}, {"longname": "Historical Congressional District CA-7, 53rd-57th Congress, USA", "shortname": "CA-07 [53rd-57th Congress]", "row_type": "Historical Congressional District"}, {"longname": "Historical Congressional District CA-6, 49th-52nd Congress, USA", "shortname": "CA-06 [49th-52nd Congress]", "row_type": "Historical Congressional District"}, {"longname": "Historical Congressional District CA-4, 48th Congress, USA", "shortname": "CA-04 [48th Congress]", "row_type": "Historical Congressional District"}, {"longname": "Historical Congressional District CA-4, 43rd-47th Congress, USA", "shortname": "CA-04 [43rd-47th Congress]", "row_type": "Historical Congressional District"}, {"longname": "Historical Congressional District CA-1, 40th-42nd Congress, USA", "shortname": "CA-01 [40th-42nd Congress]", "row_type": "Historical Congressional District"}, {"longname": "Historical Congressional District CA-1, 39th Congress, USA", "shortname": "CA-01 [39th Congress]", "row_type": "Historical Congressional District"}, {"longname": "CA-HD036, USA", "shortname": "CA-HD036", "row_type": "State House District"}, {"longname": "CA-SD018, USA", "shortname": "CA-SD018", "row_type": "State Senate District"}, {"longname": "CA-25, USA", "shortname": "CA-25", "row_type": "Congressional District"}, {"longname": "El Centro CCD [CCD], Imperial County, California, USA", "shortname": "El Centro CCD", "row_type": "CCD"}], "contains": [], "borders": [{"longname": "92243, USA", "shortname": "92243", "row_type": "ZIP"}, {"longname": "92251, USA", "shortname": "92251", "row_type": "ZIP"}], "intersects": [{"longname": "Seeley CDP, California, USA", "shortname": "Seeley CDP", "row_type": "City"}, {"longname": "Central Union High School District, California, USA", "shortname": "Central Union High School District", "row_type": "School District"}, {"longname": "Imperial Unified School District, California, USA", "shortname": "Imperial Unified School District", "row_type": "School District"}, {"longname": "Seeley Union Elementary School District, California, USA", "shortname": "Seeley Union Elementary School District", "row_type": "School District"}]}}