{"shortname": "MS-SD047", "longname": "MS-SD047, USA", "source": "Census", "article_type": "State Senate District", "rows": [{"statname": "Population", "statval": 59203.0, "ordinal": 1448, "overall_ordinal": 18379, "percentile_by_population": 0.05510932564053084}, {"statname": "PW Density (r=1km)", "statval": 239.2998001416028, "ordinal": 1754, "overall_ordinal": 78421, "percentile_by_population": 0.04636588535673525}, {"statname": "AW Density", "statval": 26.549896782772638, "ordinal": 1474, "overall_ordinal": 100048, "percentile_by_population": 0.15080880037949962}, {"statname": "White %", "statval": 0.7843690353529382, "ordinal": 684, "overall_ordinal": 84244, "percentile_by_population": 0.7677084643700405}, {"statname": "Hispanic %", "statval": 0.037481208722530954, "ordinal": 1554, "overall_ordinal": 85819, "percentile_by_population": 0.12721581383775205}, {"statname": "Black %", "statval": 0.10055233687482053, "ordinal": 625, "overall_ordinal": 31834, "percentile_by_population": 0.6215515451977505}, {"statname": "Asian %", "statval": 0.022161039136530242, "ordinal": 950, "overall_ordinal": 37892, "percentile_by_population": 0.3755221282435659}, {"statname": "Native %", "statval": 0.00410452173031772, "ordinal": 696, "overall_ordinal": 46271, "percentile_by_population": 0.7593918716877921}, {"statname": "Hawaiian / PI %", "statval": 0.0006756414370893367, "ordinal": 656, "overall_ordinal": 32587, "percentile_by_population": 0.6260796779690259}, {"statname": "Other / Mixed %", "statval": 0.05065621674577302, "ordinal": 588, "overall_ordinal": 42255, "percentile_by_population": 0.7257611004986411}, {"statname": "High School %", "statval": 0.878370017508569, "ordinal": 1483, "overall_ordinal": 107788, "percentile_by_population": 0.3028125738980515}, {"statname": "Undergrad %", "statval": 0.17359556779210317, "ordinal": 1762, "overall_ordinal": 102691, "percentile_by_population": 0.07805389891833747}, {"statname": "Grad %", "statval": 0.06502365935068022, "ordinal": 1604, "overall_ordinal": 84905, "percentile_by_population": 0.13586363184181527}, {"statname": "Undergrad STEM %", "statval": 0.4678991921889317, "ordinal": 425, "overall_ordinal": 46665, "percentile_by_population": 0.7536960423743959}, {"statname": "Undergrad Humanities %", "statval": 0.3754828735378051, "ordinal": 886, "overall_ordinal": 82044, "percentile_by_population": 0.6496188369191346}, {"statname": "Undergrad Business %", "statval": 0.15661793427326323, "ordinal": 1623, "overall_ordinal": 94916, "percentile_by_population": 0.11515435482147074}, {"statname": "Silent %", "statval": 0.0473028464389515, "ordinal": 1621, "overall_ordinal": 121897, "percentile_by_population": 0.16744182550683862}, {"statname": "Boomer %", "statval": 0.24271233359959682, "ordinal": 750, "overall_ordinal": 86749, "percentile_by_population": 0.6688500108126825}, {"statname": "Gen X %", "statval": 0.19687404053908644, "ordinal": 481, "overall_ordinal": 50704, "percentile_by_population": 0.6938006807454944}, {"statname": "Millennial %", "statval": 0.18993279634677748, "ordinal": 1075, "overall_ordinal": 57918, "percentile_by_population": 0.3858713353187584}, {"statname": "Gen Z %", "statval": 0.21266090368351398, "ordinal": 440, "overall_ordinal": 35357, "percentile_by_population": 0.7665154201235667}, {"statname": "Gen Alpha %", "statval": 0.11051707939207368, "ordinal": 1417, "overall_ordinal": 84205, "percentile_by_population": 0.2620148511667696}, {"statname": "Household Income < $50k %", "statval": 0.4325919767321176, "ordinal": 620, "overall_ordinal": 62227, "percentile_by_population": 0.7150388341100865}, {"statname": "Household Income $50k - $100k %", "statval": 0.32252135424031336, "ordinal": 609, "overall_ordinal": 65010, "percentile_by_population": 0.7627588867104429}, {"statname": "Household Income > $100k %", "statval": 0.2448866690275691, "ordinal": 1331, "overall_ordinal": 83830, "percentile_by_population": 0.2651654855595845}, {"statname": "Individual Income < $50k %", "statval": 0.7175547715068419, "ordinal": 591, "overall_ordinal": 65348, "percentile_by_population": 0.7265688288008549}, {"statname": "Individual Income $50k - $100k %", "statval": 0.22237441027394877, "ordinal": 1203, "overall_ordinal": 80000, "percentile_by_population": 0.39074092137986227}, {"statname": "Individual Income > $100k %", "statval": 0.06007081821920915, "ordinal": 1510, "overall_ordinal": 90017, "percentile_by_population": 0.18041006357557376}, {"statname": "Housing Units per Adult", "statval": 0.5226113943693195, "ordinal": 1408, "overall_ordinal": 114550, "percentile_by_population": 0.3779005041895426}, {"statname": "Vacancy %", "statval": 0.09030752916224814, "ordinal": 848, "overall_ordinal": 84880, "percentile_by_population": 0.6120605653162088}, {"statname": "1BR Rent < $750 %", "statval": 0.6141773948781905, "ordinal": 634, "overall_ordinal": 67719, "percentile_by_population": 0.7782265946662867}, {"statname": "1BR Rent $750 - $1500 %", "statval": 0.38582260512180966, "ordinal": 1132, "overall_ordinal": 49940, "percentile_by_population": 0.35242002974630504}, {"statname": "1BR Rent > $1500 %", "statval": 0.0, "ordinal": 1798, "overall_ordinal": 100450, "percentile_by_population": 0.020414691587491207}, {"statname": "2BR Rent < $750 %", "statval": 0.28383147903512757, "ordinal": 690, "overall_ordinal": 77628, "percentile_by_population": 0.747740486768317}, {"statname": "2BR Rent $750 - $1500 %", "statval": 0.7150672310821635, "ordinal": 472, "overall_ordinal": 35630, "percentile_by_population": 0.806140085926299}, {"statname": "2BR Rent > $1500 %", "statval": 0.0011012898827090093, "ordinal": 1848, "overall_ordinal": 68125, "percentile_by_population": 0.01745988211817895}, {"statname": "Commute Car %", "statval": 0.9408124462929565, "ordinal": 50, "overall_ordinal": 22327, "percentile_by_population": 0.9866326867548353}, {"statname": "Commute Bike %", "statval": 0.0004336125117931724, "ordinal": 1853, "overall_ordinal": 70871, "percentile_by_population": 0.021883234904988558}, {"statname": "Commute Walk %", "statval": 0.006219582635016594, "ordinal": 1821, "overall_ordinal": 111272, "percentile_by_population": 0.03910069332018096}, {"statname": "Commute Transit %", "statval": 0.0012364360146406156, "ordinal": 1740, "overall_ordinal": 76648, "percentile_by_population": 0.048732427939778056}, {"statname": "Commute Work From Home %", "statval": 0.039999568635259476, "ordinal": 1802, "overall_ordinal": 117969, "percentile_by_population": 0.039573417122330756}, {"statname": "Commute Time < 15 min %", "statval": 0.18033680977638392, "ordinal": 1687, "overall_ordinal": 118830, "percentile_by_population": 0.19486274169719375}, {"statname": "Commute Time 15 - 29 min %", "statval": 0.3872568572742842, "ordinal": 725, "overall_ordinal": 52913, "percentile_by_population": 0.6641910428904201}, {"statname": "Commute Time 30 - 59 min %", "statval": 0.33697553711045564, "ordinal": 452, "overall_ordinal": 44222, "percentile_by_population": 0.6812268437655302}, {"statname": "Commute Time > 60 min %", "statval": 0.0954307958388762, "ordinal": 497, "overall_ordinal": 50508, "percentile_by_population": 0.6420524322827492}, {"statname": "2020 Presidential Election", "statval": -0.6463743177754089, "ordinal": 1912, "overall_ordinal": 133958, "percentile_by_population": 0.005606090458362245}, {"statname": "2016 Presidential Election", "statval": -0.6798540815274515, "ordinal": 1927, "overall_ordinal": 140522, "percentile_by_population": 0.0029538843264768078}, {"statname": "PW Density (r=250m)", "statval": 1147.7937815006178, "ordinal": 1449, "overall_ordinal": 60953, "percentile_by_population": 0.15309830819311088}, {"statname": "PW Density (r=500m)", "statval": 432.6304653902897, "ordinal": 1687, "overall_ordinal": 75544, "percentile_by_population": 0.06682260140635743}, {"statname": "PW Density (r=2km)", "statval": 164.15358523915793, "ordinal": 1735, "overall_ordinal": 74574, "percentile_by_population": 0.04886419125694308}, {"statname": "PW Density (r=4km)", "statval": 118.9942848281386, "ordinal": 1648, "overall_ordinal": 70650, "percentile_by_population": 0.07163099501325032}], "related": {"same_geography": [], "contained_by": [{"longname": "Mississippi, USA", "shortname": "Mississippi", "row_type": "State"}, {"longname": "Historical Congressional District MS-4, 113th-117th Congress, USA", "shortname": "MS-04 [113th-117th Congress]", "row_type": "Historical Congressional District"}, {"longname": "Historical Congressional District MS-4, 108th-112th Congress, USA", "shortname": "MS-04 [108th-112th Congress]", "row_type": "Historical Congressional District"}, {"longname": "Historical Congressional District MS-5, 103rd-107th Congress, USA", "shortname": "MS-05 [103rd-107th Congress]", "row_type": "Historical Congressional District"}, {"longname": "Historical Congressional District MS-5, 99th-102nd Congress, USA", "shortname": "MS-05 [99th-102nd Congress]", "row_type": "Historical Congressional District"}, {"longname": "Historical Congressional District MS-5, 98th Congress, USA", "shortname": "MS-05 [98th Congress]", "row_type": "Historical Congressional District"}, {"longname": "Historical Congressional District MS-5, 93rd-97th Congress, USA", "shortname": "MS-05 [93rd-97th Congress]", "row_type": "Historical Congressional District"}, {"longname": "Historical Congressional District MS-5, 90th-92nd Congress, USA", "shortname": "MS-05 [90th-92nd Congress]", "row_type": "Historical Congressional District"}, {"longname": "Historical Congressional District MS-5, 88th-89th Congress, USA", "shortname": "MS-05 [88th-89th Congress]", "row_type": "Historical Congressional District"}, {"longname": "Historical Congressional District MS-6, 85th-87th Congress, USA", "shortname": "MS-06 [85th-87th Congress]", "row_type": "Historical Congressional District"}, {"longname": "Historical Congressional District MS-6, 83rd-84th Congress, USA", "shortname": "MS-06 [83rd-84th Congress]", "row_type": "Historical Congressional District"}, {"longname": "Historical Congressional District MS-6, 73rd-82nd Congress, USA", "shortname": "MS-06 [73rd-82nd Congress]", "row_type": "Historical Congressional District"}, {"longname": "Historical Congressional District MS-6, 66th-72nd Congress, USA", "shortname": "MS-06 [66th-72nd Congress]", "row_type": "Historical Congressional District"}, {"longname": "Historical Congressional District MS-6, 62nd-65th Congress, USA", "shortname": "MS-06 [62nd-65th Congress]", "row_type": "Historical Congressional District"}, {"longname": "Historical Congressional District MS-6, 58th-61st Congress, USA", "shortname": "MS-06 [58th-61st Congress]", "row_type": "Historical Congressional District"}, {"longname": "Historical Congressional District MS-6, 48th-57th Congress, USA", "shortname": "MS-06 [48th-57th Congress]", "row_type": "Historical Congressional District"}, {"longname": "Historical Congressional District MS-5, 46th-47th Congress, USA", "shortname": "MS-05 [46th-47th Congress]", "row_type": "Historical Congressional District"}, {"longname": "Historical Congressional District MS-5, 45th Congress, USA", "shortname": "MS-05 [45th Congress]", "row_type": "Historical Congressional District"}, {"longname": "Historical Congressional District MS-6, 43rd-44th Congress, USA", "shortname": "MS-06 [43rd-44th Congress]", "row_type": "Historical Congressional District"}, {"longname": "Historical Congressional District MS-5, 41st-42nd Congress, USA", "shortname": "MS-05 [41st-42nd Congress]", "row_type": "Historical Congressional District"}, {"longname": "Historical Congressional District MS-5, 35th-36th Congress, USA", "shortname": "MS-05 [35th-36th Congress]", "row_type": "Historical Congressional District"}, {"longname": "Historical Congressional District MS-5, 34th Congress, USA", "shortname": "MS-05 [34th Congress]", "row_type": "Historical Congressional District"}, {"longname": "Historical Congressional District MS-4, 33rd Congress, USA", "shortname": "MS-04 [33rd Congress]", "row_type": "Historical Congressional District"}, {"longname": "Historical Congressional District MS-4, 30th-32nd Congress, USA", "shortname": "MS-04 [30th-32nd Congress]", "row_type": "Historical Congressional District"}, {"longname": "MS-04, USA", "shortname": "MS-04", "row_type": "Congressional District"}], "contains": [{"longname": "District 1 [CCD], Stone County, Mississippi, USA", "shortname": "District 1", "row_type": "CCD"}, {"longname": "District 4 [CCD], Stone County, Mississippi, USA", "shortname": "District 4", "row_type": "CCD"}, {"longname": "District 5 [CCD], Stone County, Mississippi, USA", "shortname": "District 5", "row_type": "CCD"}, {"longname": "Hurley CDP, Mississippi, USA", "shortname": "Hurley CDP", "row_type": "City"}, {"longname": "Saucier CDP, Mississippi, USA", "shortname": "Saucier CDP", "row_type": "City"}, {"longname": "St. Martin CDP, Mississippi, USA", "shortname": "St. Martin CDP", "row_type": "City"}, {"longname": "Wade CDP, Mississippi, USA", "shortname": "Wade CDP", "row_type": "City"}, {"longname": "Wiggins city, Mississippi, USA", "shortname": "Wiggins city", "row_type": "City"}], "borders": [{"longname": "Mobile-Daphne-Fairhope CSA, AL, USA", "shortname": "Mobile-Daphne-Fairhope CSA", "row_type": "CSA"}, {"longname": "Hattiesburg MSA, MS, USA", "shortname": "Hattiesburg MSA", "row_type": "MSA"}, {"longname": "Mobile MSA, AL, USA", "shortname": "Mobile MSA", "row_type": "MSA"}, {"longname": "Forrest County, Mississippi, USA", "shortname": "Forrest County", "row_type": "County"}, {"longname": "George County, Mississippi, USA", "shortname": "George County", "row_type": "County"}, {"longname": "Mobile County, Alabama, USA", "shortname": "Mobile County", "row_type": "County"}, {"longname": "Perry County, Mississippi, USA", "shortname": "Perry County", "row_type": "County"}, {"longname": "Historical Congressional District AL-1, 113th-117th Congress, USA", "shortname": "AL-01 [113th-117th Congress]", "row_type": "Historical Congressional District"}, {"longname": "Historical Congressional District AL-1, 108th-112th Congress, USA", "shortname": "AL-01 [108th-112th Congress]", "row_type": "Historical Congressional District"}, {"longname": "Historical Congressional District AL-1, 103rd-107th Congress, USA", "shortname": "AL-01 [103rd-107th Congress]", "row_type": "Historical Congressional District"}, {"longname": "Historical Congressional District AL-1, 98th-102nd Congress, USA", "shortname": "AL-01 [98th-102nd Congress]", "row_type": "Historical Congressional District"}, {"longname": "Historical Congressional District AL-1, 93rd-97th Congress, USA", "shortname": "AL-01 [93rd-97th Congress]", "row_type": "Historical Congressional District"}, {"longname": "Historical Congressional District AL-1, 90th-92nd Congress, USA", "shortname": "AL-01 [90th-92nd Congress]", "row_type": "Historical Congressional District"}, {"longname": "Historical Congressional District AL-1, 89th Congress, USA", "shortname": "AL-01 [89th Congress]", "row_type": "Historical Congressional District"}, {"longname": "Historical Congressional District AL-1, 73rd-87th Congress, USA", "shortname": "AL-01 [73rd-87th Congress]", "row_type": "Historical Congressional District"}, {"longname": "Historical Congressional District AL-1, 65th-72nd Congress, USA", "shortname": "AL-01 [65th-72nd Congress]", "row_type": "Historical Congressional District"}, {"longname": "Historical Congressional District AL-1, 63rd-64th Congress, USA", "shortname": "AL-01 [63rd-64th Congress]", "row_type": "Historical Congressional District"}, {"longname": "Historical Congressional District AL-1, 58th-62nd Congress, USA", "shortname": "AL-01 [58th-62nd Congress]", "row_type": "Historical Congressional District"}, {"longname": "Historical Congressional District AL-1, 53rd-57th Congress, USA", "shortname": "AL-01 [53rd-57th Congress]", "row_type": "Historical Congressional District"}, {"longname": "Historical Congressional District AL-1, 49th-52nd Congress, USA", "shortname": "AL-01 [49th-52nd Congress]", "row_type": "Historical Congressional District"}, {"longname": "Historical Congressional District AL-1, 45th-48th Congress, USA", "shortname": "AL-01 [45th-48th Congress]", "row_type": "Historical Congressional District"}, {"longname": "Historical Congressional District AL-1, 43rd-44th Congress, USA", "shortname": "AL-01 [43rd-44th Congress]", "row_type": "Historical Congressional District"}, {"longname": "Historical Congressional District AL-1, 40th-42nd Congress, USA", "shortname": "AL-01 [40th-42nd Congress]", "row_type": "Historical Congressional District"}, {"longname": "Historical Congressional District AL-1, 34th-36th Congress, USA", "shortname": "AL-01 [34th-36th Congress]", "row_type": "Historical Congressional District"}, {"longname": "Historical Congressional District AL-1, 28th-33rd Congress, USA", "shortname": "AL-01 [28th-33rd Congress]", "row_type": "Historical Congressional District"}, {"longname": "Historical Congressional District AL-5, 23rd-26th Congress, USA", "shortname": "AL-05 [23rd-26th Congress]", "row_type": "Historical Congressional District"}, {"longname": "Historical Congressional District AL-3, 18th-22nd Congress, USA", "shortname": "AL-03 [18th-22nd Congress]", "row_type": "Historical Congressional District"}, {"longname": "AL-HD100, USA", "shortname": "AL-HD100", "row_type": "State House District"}, {"longname": "AL-HD102, USA", "shortname": "AL-HD102", "row_type": "State House District"}, {"longname": "MS-HD104, USA", "shortname": "MS-HD104", "row_type": "State House District"}, {"longname": "MS-HD105, USA", "shortname": "MS-HD105", "row_type": "State House District"}, {"longname": "MS-HD111, USA", "shortname": "MS-HD111", "row_type": "State House District"}, {"longname": "MS-HD112, USA", "shortname": "MS-HD112", "row_type": "State House District"}, {"longname": "MS-HD115, USA", "shortname": "MS-HD115", "row_type": "State House District"}, {"longname": "MS-HD121, USA", "shortname": "MS-HD121", "row_type": "State House District"}, {"longname": "AL-SD034, USA", "shortname": "AL-SD034", "row_type": "State Senate District"}, {"longname": "MS-SD040, USA", "shortname": "MS-SD040", "row_type": "State Senate District"}, {"longname": "MS-SD043, USA", "shortname": "MS-SD043", "row_type": "State Senate District"}, {"longname": "MS-SD045, USA", "shortname": "MS-SD045", "row_type": "State Senate District"}, {"longname": "MS-SD046, USA", "shortname": "MS-SD046", "row_type": "State Senate District"}, {"longname": "MS-SD050, USA", "shortname": "MS-SD050", "row_type": "State Senate District"}, {"longname": "MS-SD051, USA", "shortname": "MS-SD051", "row_type": "State Senate District"}, {"longname": "MS-SD052, USA", "shortname": "MS-SD052", "row_type": "State Senate District"}, {"longname": "AL-01, USA", "shortname": "AL-01", "row_type": "Congressional District"}], "intersects": [{"longname": "Gulfport-Biloxi-Pascagoula MSA, MS, USA", "shortname": "Gulfport-Biloxi-Pascagoula MSA", "row_type": "MSA"}, {"longname": "Harrison County, Mississippi, USA", "shortname": "Harrison County", "row_type": "County"}, {"longname": "Jackson County, Mississippi, USA", "shortname": "Jackson County", "row_type": "County"}, {"longname": "Stone County, Mississippi, USA", "shortname": "Stone County", "row_type": "County"}, {"longname": "MS-HD033, USA", "shortname": "MS-HD033", "row_type": "State House District"}, {"longname": "MS-HD093, USA", "shortname": "MS-HD093", "row_type": "State House District"}, {"longname": "MS-HD095, USA", "shortname": "MS-HD095", "row_type": "State House District"}, {"longname": "MS-HD107, USA", "shortname": "MS-HD107", "row_type": "State House District"}, {"longname": "MS-HD109, USA", "shortname": "MS-HD109", "row_type": "State House District"}, {"longname": "MS-HD114, USA", "shortname": "MS-HD114", "row_type": "State House District"}, {"longname": "MS-HD116, USA", "shortname": "MS-HD116", "row_type": "State House District"}]}}