{"shortname": "Raymond city", "longname": "Raymond city, Mississippi, USA", "source": "Census", "article_type": "City", "rows": [{"statname": "Population", "statval": 1960.0, "ordinal": 11427, "overall_ordinal": 85726, "percentile_by_population": 0.04618159911469555}, {"statname": "PW Density (r=1km)", "statval": 459.91361191871937, "ordinal": 9390, "overall_ordinal": 59375, "percentile_by_population": 0.0930964529646987}, {"statname": "AW Density", "statval": 263.151339291511, "ordinal": 15820, "overall_ordinal": 54412, "percentile_by_population": 0.0749774642103368}, {"statname": "White %", "statval": 0.38979591836734695, "ordinal": 27673, "overall_ordinal": 131600, "percentile_by_population": 0.3397730793744995}, {"statname": "Hispanic %", "statval": 0.01479591836734694, "ordinal": 26123, "overall_ordinal": 127323, "percentile_by_population": 0.01630668684072012}, {"statname": "Black %", "statval": 0.573469387755102, "ordinal": 885, "overall_ordinal": 4868, "percentile_by_population": 0.9737697877073116}, {"statname": "Asian %", "statval": 0.0020408163265306124, "ordinal": 20399, "overall_ordinal": 112279, "percentile_by_population": 0.032484600585215406}, {"statname": "Native %", "statval": 0.0010204081632653062, "ordinal": 20044, "overall_ordinal": 108841, "percentile_by_population": 0.12714724328976335}, {"statname": "Hawaiian / PI %", "statval": 0.0010204081632653062, "ordinal": 4698, "overall_ordinal": 24086, "percentile_by_population": 0.6756092003124214}, {"statname": "Other / Mixed %", "statval": 0.01785714285714286, "ordinal": 27787, "overall_ordinal": 137572, "percentile_by_population": 0.04217670564145681}, {"statname": "High School %", "statval": 0.9718743300478832, "ordinal": 3341, "overall_ordinal": 13857, "percentile_by_population": 0.9405869234309968}, {"statname": "Undergrad %", "statval": 0.35424408310664884, "ordinal": 5883, "overall_ordinal": 33602, "percentile_by_population": 0.5861503822126399}, {"statname": "Grad %", "statval": 0.19351020242583597, "ordinal": 3081, "overall_ordinal": 17510, "percentile_by_population": 0.8307629790817477}, {"statname": "Undergrad STEM %", "statval": 0.3252097379866105, "ordinal": 24501, "overall_ordinal": 127811, "percentile_by_population": 0.05163208150821641}, {"statname": "Undergrad Humanities %", "statval": 0.4484549856013178, "ordinal": 10498, "overall_ordinal": 40297, "percentile_by_population": 0.9121544737433971}, {"statname": "Undergrad Business %", "statval": 0.22633527641207177, "ordinal": 9265, "overall_ordinal": 40344, "percentile_by_population": 0.6927673332404832}, {"statname": "Silent %", "statval": 0.05183159424557824, "ordinal": 23199, "overall_ordinal": 114005, "percentile_by_population": 0.3765557598319388}, {"statname": "Boomer %", "statval": 0.21284154047088497, "ordinal": 23841, "overall_ordinal": 115665, "percentile_by_population": 0.5630280644304044}, {"statname": "Gen X %", "statval": 0.089652375989413, "ordinal": 30992, "overall_ordinal": 149606, "percentile_by_population": 0.0085086741687449}, {"statname": "Millennial %", "statval": 0.09173858784653469, "ordinal": 29821, "overall_ordinal": 146368, "percentile_by_population": 0.011536028742135995}, {"statname": "Gen Z %", "statval": 0.5361126458821972, "ordinal": 131, "overall_ordinal": 732, "percentile_by_population": 0.9965230547152919}, {"statname": "Gen Alpha %", "statval": 0.017823255565391806, "ordinal": 31371, "overall_ordinal": 150913, "percentile_by_population": 0.003207570797095771}, {"statname": "Household Income < $50k %", "statval": 0.41324200913242015, "ordinal": 15368, "overall_ordinal": 71252, "percentile_by_population": 0.621833321949097}, {"statname": "Household Income $50k - $100k %", "statval": 0.36529680365296807, "ordinal": 6554, "overall_ordinal": 26212, "percentile_by_population": 0.9327126879505647}, {"statname": "Household Income > $100k %", "statval": 0.2214611872146119, "ordinal": 19219, "overall_ordinal": 96712, "percentile_by_population": 0.23361725662399568}, {"statname": "Individual Income < $50k %", "statval": 0.7373929590865843, "ordinal": 12069, "overall_ordinal": 52941, "percentile_by_population": 0.764337340413249}, {"statname": "Individual Income $50k - $100k %", "statval": 0.219790675547098, "ordinal": 16544, "overall_ordinal": 82593, "percentile_by_population": 0.39377751863323884}, {"statname": "Individual Income > $100k %", "statval": 0.0428163653663178, "ordinal": 23418, "overall_ordinal": 118023, "percentile_by_population": 0.12235516681697567}, {"statname": "Housing Units per Adult", "statval": 0.2645739910313901, "ordinal": 31699, "overall_ordinal": 151804, "percentile_by_population": 0.0027791714522973354}, {"statname": "Vacancy %", "statval": 0.0423728813559322, "ordinal": 27209, "overall_ordinal": 133119, "percentile_by_population": 0.20424135901519858}, {"statname": "1BR Rent < $750 %", "statval": 0.6077552443033831, "ordinal": 14125, "overall_ordinal": 68157, "percentile_by_population": 0.80100705866059}, {"statname": "1BR Rent $750 - $1500 %", "statval": 0.392244755696617, "ordinal": 8107, "overall_ordinal": 49322, "percentile_by_population": 0.39874674075209815}, {"statname": "1BR Rent > $1500 %", "statval": 0.0, "ordinal": 19377, "overall_ordinal": 112702, "percentile_by_population": 0.07907419224861068}, {"statname": "2BR Rent < $750 %", "statval": 0.8235294117647058, "ordinal": 6089, "overall_ordinal": 22581, "percentile_by_population": 0.9770204461560452}, {"statname": "2BR Rent $750 - $1500 %", "statval": 0.1764705882352941, "ordinal": 21501, "overall_ordinal": 113917, "percentile_by_population": 0.13883601236054455}, {"statname": "2BR Rent > $1500 %", "statval": 0.0, "ordinal": 24457, "overall_ordinal": 130217, "percentile_by_population": 0.04056118354733851}, {"statname": "Commute Car %", "statval": 0.9316057719084616, "ordinal": 8474, "overall_ordinal": 29364, "percentile_by_population": 0.9236852295350969}, {"statname": "Commute Bike %", "statval": 0.0, "ordinal": 26463, "overall_ordinal": 137064, "percentile_by_population": 0.04168382416636274}, {"statname": "Commute Walk %", "statval": 0.04020393253963926, "ordinal": 6457, "overall_ordinal": 30407, "percentile_by_population": 0.7977587937490256}, {"statname": "Commute Transit %", "statval": 0.004638915293035299, "ordinal": 8910, "overall_ordinal": 57154, "percentile_by_population": 0.2682527669717806}, {"statname": "Commute Work From Home %", "statval": 0.023551380258863545, "ordinal": 26117, "overall_ordinal": 135034, "percentile_by_population": 0.04014765917978991}, {"statname": "Commute Time < 15 min %", "statval": 0.3027382111946424, "ordinal": 13757, "overall_ordinal": 63401, "percentile_by_population": 0.7130357064250754}, {"statname": "Commute Time 15 - 29 min %", "statval": 0.42029010148490775, "ordinal": 8095, "overall_ordinal": 38809, "percentile_by_population": 0.6999222849147089}, {"statname": "Commute Time 30 - 59 min %", "statval": 0.2546551081944024, "ordinal": 16991, "overall_ordinal": 82221, "percentile_by_population": 0.3865933785498391}, {"statname": "Commute Time > 60 min %", "statval": 0.02231657912604745, "ordinal": 27456, "overall_ordinal": 135891, "percentile_by_population": 0.04488936782465791}, {"statname": "2020 Presidential Election", "statval": -0.15772091162335933, "ordinal": 11459, "overall_ordinal": 65184, "percentile_by_population": 0.2051991362986837}, {"statname": "2016 Presidential Election", "statval": -0.19683315872247614, "ordinal": 11892, "overall_ordinal": 66546, "percentile_by_population": 0.2107158252843876}, {"statname": "PW Density (r=250m)", "statval": 1788.6858891647141, "ordinal": 5473, "overall_ordinal": 39861, "percentile_by_population": 0.22861488341795322}, {"statname": "PW Density (r=500m)", "statval": 1012.1487838469652, "ordinal": 6104, "overall_ordinal": 43741, "percentile_by_population": 0.1904138469972425}, {"statname": "PW Density (r=2km)", "statval": 189.5713203512928, "ordinal": 11790, "overall_ordinal": 71358, "percentile_by_population": 0.05756286835456759}, {"statname": "PW Density (r=4km)", "statval": 73.87923737424836, "ordinal": 13769, "overall_ordinal": 80175, "percentile_by_population": 0.04555118284325621}], "related": {"same_geography": [], "contained_by": [{"longname": "Mississippi, USA", "shortname": "Mississippi", "row_type": "State"}, {"longname": "Jackson-Vicksburg-Brookhaven CSA, MS, USA", "shortname": "Jackson-Vicksburg-Brookhaven CSA", "row_type": "CSA"}, {"longname": "Jackson MSA, MS, USA", "shortname": "Jackson MSA", "row_type": "MSA"}, {"longname": "Hinds County, Mississippi, USA", "shortname": "Hinds County", "row_type": "County"}, {"longname": "Historical Congressional District MS-2, 113th-117th Congress, USA", "shortname": "MS-02 [113th-117th Congress]", "row_type": "Historical Congressional District"}, {"longname": "Historical Congressional District MS-2, 108th-112th Congress, USA", "shortname": "MS-02 [108th-112th Congress]", "row_type": "Historical Congressional District"}, {"longname": "Historical Congressional District MS-4, 103rd-107th Congress, USA", "shortname": "MS-04 [103rd-107th Congress]", "row_type": "Historical Congressional District"}, {"longname": "Historical Congressional District MS-2, 99th-102nd Congress, USA", "shortname": "MS-02 [99th-102nd Congress]", "row_type": "Historical Congressional District"}, {"longname": "Historical Congressional District MS-4, 98th Congress, USA", "shortname": "MS-04 [98th Congress]", "row_type": "Historical Congressional District"}, {"longname": "Historical Congressional District MS-4, 93rd-97th Congress, USA", "shortname": "MS-04 [93rd-97th Congress]", "row_type": "Historical Congressional District"}, {"longname": "Historical Congressional District MS-3, 90th-92nd Congress, USA", "shortname": "MS-03 [90th-92nd Congress]", "row_type": "Historical Congressional District"}, {"longname": "Historical Congressional District MS-3, 88th-89th Congress, USA", "shortname": "MS-03 [88th-89th Congress]", "row_type": "Historical Congressional District"}, {"longname": "Historical Congressional District MS-4, 85th-87th Congress, USA", "shortname": "MS-04 [85th-87th Congress]", "row_type": "Historical Congressional District"}, {"longname": "Historical Congressional District MS-4, 83rd-84th Congress, USA", "shortname": "MS-04 [83rd-84th Congress]", "row_type": "Historical Congressional District"}, {"longname": "Historical Congressional District MS-7, 73rd-82nd Congress, USA", "shortname": "MS-07 [73rd-82nd Congress]", "row_type": "Historical Congressional District"}, {"longname": "Historical Congressional District MS-8, 66th-72nd Congress, USA", "shortname": "MS-08 [66th-72nd Congress]", "row_type": "Historical Congressional District"}, {"longname": "Historical Congressional District MS-8, 62nd-65th Congress, USA", "shortname": "MS-08 [62nd-65th Congress]", "row_type": "Historical Congressional District"}, {"longname": "Historical Congressional District MS-8, 58th-61st Congress, USA", "shortname": "MS-08 [58th-61st Congress]", "row_type": "Historical Congressional District"}, {"longname": "Historical Congressional District MS-7, 48th-57th Congress, USA", "shortname": "MS-07 [48th-57th Congress]", "row_type": "Historical Congressional District"}, {"longname": "Historical Congressional District MS-5, 46th-47th Congress, USA", "shortname": "MS-05 [46th-47th Congress]", "row_type": "Historical Congressional District"}, {"longname": "Historical Congressional District MS-5, 45th Congress, USA", "shortname": "MS-05 [45th Congress]", "row_type": "Historical Congressional District"}, {"longname": "Historical Congressional District MS-5, 43rd-44th Congress, USA", "shortname": "MS-05 [43rd-44th Congress]", "row_type": "Historical Congressional District"}, {"longname": "Historical Congressional District MS-4, 41st-42nd Congress, USA", "shortname": "MS-04 [41st-42nd Congress]", "row_type": "Historical Congressional District"}, {"longname": "Historical Congressional District MS-4, 35th-36th Congress, USA", "shortname": "MS-04 [35th-36th Congress]", "row_type": "Historical Congressional District"}, {"longname": "Historical Congressional District MS-4, 34th Congress, USA", "shortname": "MS-04 [34th Congress]", "row_type": "Historical Congressional District"}, {"longname": "Historical Congressional District MS-3, 33rd Congress, USA", "shortname": "MS-03 [33rd Congress]", "row_type": "Historical Congressional District"}, {"longname": "Historical Congressional District MS-3, 30th-32nd Congress, USA", "shortname": "MS-03 [30th-32nd Congress]", "row_type": "Historical Congressional District"}, {"longname": "MS-HD063, USA", "shortname": "MS-HD063", "row_type": "State House District"}, {"longname": "MS-SD027, USA", "shortname": "MS-SD027", "row_type": "State Senate District"}, {"longname": "MS-02, USA", "shortname": "MS-02", "row_type": "Congressional District"}, {"longname": "District 4 [CCD], Hinds County, Mississippi, USA", "shortname": "District 4", "row_type": "CCD"}, {"longname": "Hinds County School District, Mississippi, USA", "shortname": "Hinds County School District", "row_type": "School District"}, {"longname": "39154, USA", "shortname": "39154", "row_type": "ZIP"}], "contains": [], "borders": [], "intersects": []}}