{"shortname": "Wadena-Deer Creek School District", "longname": "Wadena-Deer Creek School District, Minnesota, USA", "source": "Census", "article_type": "School District", "rows": [{"statname": "Population", "statval": 7972.0, "ordinal": 6580, "overall_ordinal": 51284, "percentile_by_population": 0.06005072446755921}, {"statname": "PW Density (r=1km)", "statval": 312.19008714396335, "ordinal": 5581, "overall_ordinal": 70939, "percentile_by_population": 0.14517910697121128}, {"statname": "AW Density", "statval": 16.1548752277848, "ordinal": 7969, "overall_ordinal": 111046, "percentile_by_population": 0.06611340743433836}, {"statname": "White %", "statval": 0.9219769192172604, "ordinal": 2737, "overall_ordinal": 34348, "percentile_by_population": 0.9559289477702454}, {"statname": "Hispanic %", "statval": 0.021826392373306573, "ordinal": 10214, "overall_ordinal": 111951, "percentile_by_population": 0.0640335610453645}, {"statname": "Black %", "statval": 0.01166583040642248, "ordinal": 6067, "overall_ordinal": 79138, "percentile_by_population": 0.17905574393670998}, {"statname": "Asian %", "statval": 0.003637732062217762, "ordinal": 8968, "overall_ordinal": 97034, "percentile_by_population": 0.07464396967196363}, {"statname": "Native %", "statval": 0.006271951831409934, "ordinal": 3325, "overall_ordinal": 32530, "percentile_by_population": 0.8681918614003463}, {"statname": "Hawaiian / PI %", "statval": 0.0006271951831409935, "ordinal": 3222, "overall_ordinal": 34263, "percentile_by_population": 0.6224393514592319}, {"statname": "Other / Mixed %", "statval": 0.03399397892624185, "ordinal": 8968, "overall_ordinal": 98835, "percentile_by_population": 0.22516624772668115}, {"statname": "High School %", "statval": 0.8995988440578035, "ordinal": 8217, "overall_ordinal": 91089, "percentile_by_population": 0.46506678929547907}, {"statname": "Undergrad %", "statval": 0.15325298622014766, "ordinal": 10310, "overall_ordinal": 114588, "percentile_by_population": 0.10043805060795996}, {"statname": "Grad %", "statval": 0.032567175273527746, "ordinal": 12090, "overall_ordinal": 129622, "percentile_by_population": 0.027778860571157415}, {"statname": "Undergrad STEM %", "statval": 0.3433896171848014, "ordinal": 11269, "overall_ordinal": 121958, "percentile_by_population": 0.04460519710557831}, {"statname": "Undergrad Humanities %", "statval": 0.563074006452872, "ordinal": 551, "overall_ordinal": 12020, "percentile_by_population": 0.9941412767519927}, {"statname": "Undergrad Business %", "statval": 0.09353637636232674, "ordinal": 12035, "overall_ordinal": 130176, "percentile_by_population": 0.01602841264266397}, {"statname": "Silent %", "statval": 0.08888758271928565, "ordinal": 3738, "overall_ordinal": 41958, "percentile_by_population": 0.8719110533876053}, {"statname": "Boomer %", "statval": 0.22045421146974004, "ordinal": 10437, "overall_ordinal": 109191, "percentile_by_population": 0.49513981233022963}, {"statname": "Gen X %", "statval": 0.1737078814044317, "ordinal": 8606, "overall_ordinal": 95094, "percentile_by_population": 0.2240998847389124}, {"statname": "Millennial %", "statval": 0.16908069818765237, "ordinal": 7146, "overall_ordinal": 88017, "percentile_by_population": 0.17766074728489634}, {"statname": "Gen Z %", "statval": 0.21455806705791955, "ordinal": 2481, "overall_ordinal": 33493, "percentile_by_population": 0.778434775943924}, {"statname": "Gen Alpha %", "statval": 0.1333115591609706, "ordinal": 3364, "overall_ordinal": 42390, "percentile_by_population": 0.7628654876090893}, {"statname": "Household Income < $50k %", "statval": 0.518123310902067, "ordinal": 2157, "overall_ordinal": 30317, "percentile_by_population": 0.8919207287108365}, {"statname": "Household Income $50k - $100k %", "statval": 0.310210090897919, "ordinal": 7186, "overall_ordinal": 78830, "percentile_by_population": 0.6093031738290329}, {"statname": "Household Income > $100k %", "statval": 0.17166659820001404, "ordinal": 11200, "overall_ordinal": 122574, "percentile_by_population": 0.0906736341510429}, {"statname": "Individual Income < $50k %", "statval": 0.7674386251497929, "ordinal": 2731, "overall_ordinal": 35807, "percentile_by_population": 0.8786366887561277}, {"statname": "Individual Income $50k - $100k %", "statval": 0.19596769156930363, "ordinal": 9406, "overall_ordinal": 104502, "percentile_by_population": 0.2008229163717068}, {"statname": "Individual Income > $100k %", "statval": 0.03659368328090343, "ordinal": 11755, "overall_ordinal": 127366, "percentile_by_population": 0.06246980172191019}, {"statname": "Housing Units per Adult", "statval": 0.6206192582511059, "ordinal": 3325, "overall_ordinal": 42838, "percentile_by_population": 0.9086656370671552}, {"statname": "Vacancy %", "statval": 0.10553728070175439, "ordinal": 6480, "overall_ordinal": 72079, "percentile_by_population": 0.7542598403913051}, {"statname": "1BR Rent < $750 %", "statval": 0.8632676496946068, "ordinal": 4524, "overall_ordinal": 45690, "percentile_by_population": 0.899979236598732}, {"statname": "1BR Rent $750 - $1500 %", "statval": 0.1367323503053932, "ordinal": 7653, "overall_ordinal": 76888, "percentile_by_population": 0.13618024589310207}, {"statname": "1BR Rent > $1500 %", "statval": 0.0, "ordinal": 12171, "overall_ordinal": 123920, "percentile_by_population": 0.018324826731487387}, {"statname": "2BR Rent < $750 %", "statval": 0.41855110124182704, "ordinal": 6008, "overall_ordinal": 61973, "percentile_by_population": 0.8472284379572047}, {"statname": "2BR Rent $750 - $1500 %", "statval": 0.5812023164465827, "ordinal": 5027, "overall_ordinal": 58378, "percentile_by_population": 0.500195856388419}, {"statname": "2BR Rent > $1500 %", "statval": 0.00024658231159015403, "ordinal": 7151, "overall_ordinal": 68702, "percentile_by_population": 0.11228856983539859}, {"statname": "Commute Car %", "statval": 0.8582217868670783, "ordinal": 8702, "overall_ordinal": 93684, "percentile_by_population": 0.496870984470398}, {"statname": "Commute Bike %", "statval": 0.00086603551129567, "ordinal": 6899, "overall_ordinal": 67061, "percentile_by_population": 0.18033366727866718}, {"statname": "Commute Walk %", "statval": 0.02432748924882915, "ordinal": 4790, "overall_ordinal": 53581, "percentile_by_population": 0.7070581133185792}, {"statname": "Commute Transit %", "statval": 0.0016744014023801358, "ordinal": 6953, "overall_ordinal": 73869, "percentile_by_population": 0.16693108093590392}, {"statname": "Commute Work From Home %", "statval": 0.11022446109683784, "ordinal": 3123, "overall_ordinal": 40369, "percentile_by_population": 0.7007419180747896}, {"statname": "Commute Time < 15 min %", "statval": 0.5029745388181285, "ordinal": 1646, "overall_ordinal": 16218, "percentile_by_population": 0.9558042738249724}, {"statname": "Commute Time 15 - 29 min %", "statval": 0.2716045547381853, "ordinal": 9160, "overall_ordinal": 110504, "percentile_by_population": 0.14877160863239391}, {"statname": "Commute Time 30 - 59 min %", "statval": 0.181684226246927, "ordinal": 10161, "overall_ordinal": 115416, "percentile_by_population": 0.15661385687861806}, {"statname": "Commute Time > 60 min %", "statval": 0.04373668019675921, "ordinal": 10144, "overall_ordinal": 108685, "percentile_by_population": 0.21238425858667853}, {"statname": "2020 Presidential Election", "statval": -0.4539977945813287, "ordinal": 8836, "overall_ordinal": 104745, "percentile_by_population": 0.10489079352983388}, {"statname": "2016 Presidential Election", "statval": -0.4511449599794677, "ordinal": 8896, "overall_ordinal": 105830, "percentile_by_population": 0.11539948694702751}, {"statname": "PW Density (r=250m)", "statval": 597.5479924797451, "ordinal": 7552, "overall_ordinal": 88428, "percentile_by_population": 0.06947364163069547}, {"statname": "PW Density (r=500m)", "statval": 443.20634845454356, "ordinal": 5958, "overall_ordinal": 74678, "percentile_by_population": 0.13055850900110566}, {"statname": "PW Density (r=2km)", "statval": 165.90951521163714, "ordinal": 5950, "overall_ordinal": 74326, "percentile_by_population": 0.11743752143962394}, {"statname": "PW Density (r=4km)", "statval": 64.80484278983579, "ordinal": 6831, "overall_ordinal": 82937, "percentile_by_population": 0.08257166765578083}], "related": {"same_geography": [], "contained_by": [{"longname": "Minnesota, USA", "shortname": "Minnesota", "row_type": "State"}, {"longname": "Historical Congressional District MN-7, 104th-107th Congress, USA", "shortname": "MN-07 [104th-107th Congress]", "row_type": "Historical Congressional District"}, {"longname": "Historical Congressional District MN-7, 103rd Congress, USA", "shortname": "MN-07 [103rd Congress]", "row_type": "Historical Congressional District"}, {"longname": "Historical Congressional District MN-7, 98th-102nd Congress, USA", "shortname": "MN-07 [98th-102nd Congress]", "row_type": "Historical Congressional District"}, {"longname": "Historical Congressional District MN-7, 93rd-97th Congress, USA", "shortname": "MN-07 [93rd-97th Congress]", "row_type": "Historical Congressional District"}, {"longname": "Historical Congressional District MN-7, 88th-92nd Congress, USA", "shortname": "MN-07 [88th-92nd Congress]", "row_type": "Historical Congressional District"}, {"longname": "Historical Congressional District MN-5, 48th-52nd Congress, USA", "shortname": "MN-05 [48th-52nd Congress]", "row_type": "Historical Congressional District"}, {"longname": "Historical Congressional District MN-3, 43rd-47th Congress, USA", "shortname": "MN-03 [43rd-47th Congress]", "row_type": "Historical Congressional District"}, {"longname": "Historical Congressional District MN-2, 38th-42nd Congress, USA", "shortname": "MN-02 [38th-42nd Congress]", "row_type": "Historical Congressional District"}, {"longname": "MN-07, USA", "shortname": "MN-07", "row_type": "Congressional District"}], "contains": [{"longname": "Bluffton city [CCD], Otter Tail County, Minnesota, USA", "shortname": "Bluffton city", "row_type": "CCD"}, {"longname": "Compton township [CCD], Otter Tail County, Minnesota, USA", "shortname": "Compton township", "row_type": "CCD"}, {"longname": "Deer Creek city [CCD], Otter Tail County, Minnesota, USA", "shortname": "Deer Creek city", "row_type": "CCD"}, {"longname": "Leaf River township [CCD], Wadena County, Minnesota, USA", "shortname": "Leaf River township", "row_type": "CCD"}, {"longname": "Wadena city [CCD], Otter Tail County, Minnesota, USA", "shortname": "Wadena city", "row_type": "CCD"}, {"longname": "Wadena city [CCD], Wadena County, Minnesota, USA", "shortname": "Wadena city", "row_type": "CCD"}, {"longname": "Bluffton city, Minnesota, USA", "shortname": "Bluffton city", "row_type": "City"}, {"longname": "Deer Creek city, Minnesota, USA", "shortname": "Deer Creek city", "row_type": "City"}, {"longname": "Wadena city, Minnesota, USA", "shortname": "Wadena city", "row_type": "City"}], "borders": [{"longname": "Aldrich township [CCD], Wadena County, Minnesota, USA", "shortname": "Aldrich township", "row_type": "CCD"}, {"longname": "Blowers township [CCD], Otter Tail County, Minnesota, USA", "shortname": "Blowers township", "row_type": "CCD"}, {"longname": "Henning township [CCD], Otter Tail County, Minnesota, USA", "shortname": "Henning township", "row_type": "CCD"}, {"longname": "Leaf Lake township [CCD], Otter Tail County, Minnesota, USA", "shortname": "Leaf Lake township", "row_type": "CCD"}, {"longname": "Newton township [CCD], Otter Tail County, Minnesota, USA", "shortname": "Newton township", "row_type": "CCD"}, {"longname": "North Germany township [CCD], Wadena County, Minnesota, USA", "shortname": "North Germany township", "row_type": "CCD"}, {"longname": "Rockwood township [CCD], Wadena County, Minnesota, USA", "shortname": "Rockwood township", "row_type": "CCD"}, {"longname": "Stowe Prairie township [CCD], Todd County, Minnesota, USA", "shortname": "Stowe Prairie township", "row_type": "CCD"}, {"longname": "Woodside township [CCD], Otter Tail County, Minnesota, USA", "shortname": "Woodside township", "row_type": "CCD"}, {"longname": "Bertha-Hewitt Public School District, Minnesota, USA", "shortname": "Bertha-Hewitt Public School District", "row_type": "School District"}, {"longname": "Henning Public School District, Minnesota, USA", "shortname": "Henning Public School District", "row_type": "School District"}, {"longname": "New York Mills Public School District, Minnesota, USA", "shortname": "New York Mills Public School District", "row_type": "School District"}, {"longname": "Sebeka Public School District, Minnesota, USA", "shortname": "Sebeka Public School District", "row_type": "School District"}, {"longname": "Verndale Public School District, Minnesota, USA", "shortname": "Verndale Public School District", "row_type": "School District"}], "intersects": [{"longname": "Fergus Falls MSA, MN, USA", "shortname": "Fergus Falls MSA", "row_type": "MSA"}, {"longname": "Otter Tail County, Minnesota, USA", "shortname": "Otter Tail County", "row_type": "County"}, {"longname": "Wadena County, Minnesota, USA", "shortname": "Wadena County", "row_type": "County"}, {"longname": "Historical Congressional District MN-7, 113th-117th Congress, USA", "shortname": "MN-07 [113th-117th Congress]", "row_type": "Historical Congressional District"}, {"longname": "Historical Congressional District MN-8, 113th-117th Congress, USA", "shortname": "MN-08 [113th-117th Congress]", "row_type": "Historical Congressional District"}, {"longname": "Historical Congressional District MN-7, 108th-112th Congress, USA", "shortname": "MN-07 [108th-112th Congress]", "row_type": "Historical Congressional District"}, {"longname": "Historical Congressional District MN-8, 108th-112th Congress, USA", "shortname": "MN-08 [108th-112th Congress]", "row_type": "Historical Congressional District"}, {"longname": "Historical Congressional District MN-6, 74th-87th Congress, USA", "shortname": "MN-06 [74th-87th Congress]", "row_type": "Historical Congressional District"}, {"longname": "Historical Congressional District MN-9, 74th-87th Congress, USA", "shortname": "MN-09 [74th-87th Congress]", "row_type": "Historical Congressional District"}, {"longname": "Historical Congressional District MN-6, 72nd Congress, USA", "shortname": "MN-06 [72nd Congress]", "row_type": "Historical Congressional District"}, {"longname": "Historical Congressional District MN-9, 72nd Congress, USA", "shortname": "MN-09 [72nd Congress]", "row_type": "Historical Congressional District"}, {"longname": "Historical Congressional District MN-6, 64th-71st Congress, USA", "shortname": "MN-06 [64th-71st Congress]", "row_type": "Historical Congressional District"}, {"longname": "Historical Congressional District MN-9, 64th-71st Congress, USA", "shortname": "MN-09 [64th-71st Congress]", "row_type": "Historical Congressional District"}, {"longname": "Historical Congressional District MN-6, 63rd Congress, USA", "shortname": "MN-06 [63rd Congress]", "row_type": "Historical Congressional District"}, {"longname": "Historical Congressional District MN-9, 63rd Congress, USA", "shortname": "MN-09 [63rd Congress]", "row_type": "Historical Congressional District"}, {"longname": "Historical Congressional District MN-6, 58th-62nd Congress, USA", "shortname": "MN-06 [58th-62nd Congress]", "row_type": "Historical Congressional District"}, {"longname": "Historical Congressional District MN-9, 58th-62nd Congress, USA", "shortname": "MN-09 [58th-62nd Congress]", "row_type": "Historical Congressional District"}, {"longname": "Historical Congressional District MN-6, 53rd-57th Congress, USA", "shortname": "MN-06 [53rd-57th Congress]", "row_type": "Historical Congressional District"}, {"longname": "Historical Congressional District MN-7, 53rd-57th Congress, USA", "shortname": "MN-07 [53rd-57th Congress]", "row_type": "Historical Congressional District"}, {"longname": "MN-HD05B, USA", "shortname": "MN-HD05B", "row_type": "State House District"}, {"longname": "MN-HD09B, USA", "shortname": "MN-HD09B", "row_type": "State House District"}, {"longname": "MN-SD005, USA", "shortname": "MN-SD005", "row_type": "State Senate District"}, {"longname": "MN-SD009, USA", "shortname": "MN-SD009", "row_type": "State Senate District"}, {"longname": "Bluffton township [CCD], Otter Tail County, Minnesota, USA", "shortname": "Bluffton township", "row_type": "CCD"}, {"longname": "Deer Creek township [CCD], Otter Tail County, Minnesota, USA", "shortname": "Deer Creek township", "row_type": "CCD"}, {"longname": "Inman township [CCD], Otter Tail County, Minnesota, USA", "shortname": "Inman township", "row_type": "CCD"}, {"longname": "Oak Valley township [CCD], Otter Tail County, Minnesota, USA", "shortname": "Oak Valley township", "row_type": "CCD"}, {"longname": "Wadena township [CCD], Wadena County, Minnesota, USA", "shortname": "Wadena township", "row_type": "CCD"}, {"longname": "Wing River township [CCD], Wadena County, Minnesota, USA", "shortname": "Wing River township", "row_type": "CCD"}]}}